{
  "general": {
    "chairman": {
      "name": "姜長安",
      "title": "理事長",
      "img": "/general_director.jpg"
    },
    "viceChairmen": ["吳廣義", "汪秉龍"],
    "directors": [
      "王震緒", "何俊輝", "余孝先", "吳宗賢", "吳銘雄", "李正中", "李志強", "李明哲", "杜彥宏", "杜書全",
      "周世傑", "林行憲", "林志明", "姜長安", "柯富仁", "翁順峰", "張財銘", "陳永富", "陳冠州", "陳國源",
      "楊明芳", "歐耿良", "蔡宜謙", "盧豐裕", "顏光裕"
    ],
    "altDirectors": ["周賢穎", "郭加永", "曹暘正", "陳榮邦", "黃才丞", "黃貞凱", "黃建平", "楊偉森", "鄭竹明"],
    "convener": ["郝挺"],
    "supervisors": ["方振洲", "沈文義", "林嘉勳", "馬鴻方", "趙書華", "劉家瑞", "鄭光遠", "鍾惠民"],
    "altSupervisors": ["江國泉", "黃源南", "葉明水"]
  },
  "taipei": {
    "chairman": {
      "name": "歐耿良",
      "title": "理事長",
      "img": "/taipei_director.png"
    },
    "viceChairmen": ["葉明水"],
    "executiveDirectors": ["馬友樂", "陳欣德", "陳益世", "黃種智"],
    "directors": [
      "李光斌", "沈上謙", "俞伯瑋", "徐逢昇", "翁暐明", "梁厚誠", "曾仲銘", "曾金池",
      "楊明芳", "楊熙人", "劉于孜", "劉家瑞", "蔡宜兼", "蔡祈岩"
    ],
    "altDirectors": ["林柏韋", "邱文桃", "姜家宏", "洪偉騰", "許偉揚", "陳慕天", "董軒宇"],
    "convener": ["宋貴修"],
    "executiveSupervisors": ["丁明勇", "朱慶忠", "曹暘正", "游俊樺", "黃須白", "劉文章"],
    "supervisors": ["林育竹", "羅振憲"]
  },
  "hsinchu": {},
  "taichung": {},
  "kaohsiung": {},
  "shanghai": {}
}
